MANIFEST.in
README.rst
pyvenv.cfg
setup.py
test.py
docs/CREDITS.txt
docs/HISTORY.rst
docs/LICENSE.txt
src/horseman/setup.py
src/horseman/docs/LICENSE.txt
src/horseman/src/horseman/__init__.py
src/horseman/src/horseman/datastructures.py
src/horseman/src/horseman/http.py
src/horseman/src/horseman/mapping.py
src/horseman/src/horseman/meta.py
src/horseman/src/horseman/response.py
src/horseman/src/horseman/types.py
src/horseman/src/horseman.egg-info/SOURCES.txt
src/horseman/src/horseman.egg-info/dependency_links.txt
src/horseman/src/horseman.egg-info/requires.txt
src/horseman/src/horseman.egg-info/top_level.txt
src/horseman/src/horseman/parsers/__init__.py
src/horseman/src/horseman/parsers/multipart.py
src/horseman/tests/test_apiview.py
src/horseman/tests/test_content_type.py
src/horseman/tests/test_cookies.py
src/horseman/tests/test_formdata.py
src/horseman/tests/test_httperrors.py
src/horseman/tests/test_mapping.py
src/horseman/tests/test_nodes.py
src/horseman/tests/test_parser.py
src/horseman/tests/test_query.py
src/horseman/tests/test_response.py
src/horseman/tests/test_response_headers.py
src/horseman/tests/parsing/test_json.py
src/horseman/tests/parsing/test_multipart.py
src/horseman/tests/parsing/test_urlencoded.py
src/roughrider/__init__.py
src/roughrider.routing.egg-info/PKG-INFO
src/roughrider.routing.egg-info/SOURCES.txt
src/roughrider.routing.egg-info/dependency_links.txt
src/roughrider.routing.egg-info/namespace_packages.txt
src/roughrider.routing.egg-info/not-zip-safe
src/roughrider.routing.egg-info/requires.txt
src/roughrider.routing.egg-info/top_level.txt
src/roughrider/routing/__init__.py
src/roughrider/routing/components.py
src/roughrider/routing/meta.py
src/roughrider/routing/utils.py
tests/conftest.py
tests/test_namedroutes.py
tests/test_routes.py
tests/test_routing.py
tests/test_view_routing.py
tests/lib/python3.8/site-packages/bjoern.py
tests/lib/python3.8/site-packages/easy_install.py
tests/lib/python3.8/site-packages/frozendict/__init__.py
tests/lib/python3.8/site-packages/frozendict/core.py
tests/lib/python3.8/site-packages/horseman/__init__.py
tests/lib/python3.8/site-packages/horseman/datastructures.py
tests/lib/python3.8/site-packages/horseman/http.py
tests/lib/python3.8/site-packages/horseman/mapping.py
tests/lib/python3.8/site-packages/horseman/meta.py
tests/lib/python3.8/site-packages/horseman/response.py
tests/lib/python3.8/site-packages/horseman/types.py
tests/lib/python3.8/site-packages/horseman/parsers/__init__.py
